cisort/__init__.py
cisort/cisort.py
cisort/parse.py
cisort/settings.py
cisort-1.1.15.dist-info/entry_points.txt
cisort-1.1.15.dist-info/METADATA
cisort-1.1.15.dist-info/WHEEL
cisort-1.1.15.dist-info/RECORD
